Metadata-Version: 2.1
Name: netmetr-proxy
Version: 0.1.2
Summary: Helper proxy to sit between netmetr web client and backend. Adds a token/key and calls backend.
Home-page: https://gitlab.labs.nic.cz/websites/netmetr-proxy
Author: Jiri Helebrant
Author-email: jiri.helebrant@nic.cz
License: UNKNOWN
Keywords: netmetr
Platform: UNKNOWN
Classifier: Development Status :: 4 - Beta
Classifier: Programming Language :: Python
Classifier: Programming Language :: Python :: 3
Classifier: License :: OSI Approved :: GNU General Public License v3 (GPLv3)
Classifier: Operating System :: OS Independent
Requires-Python: >=3.6
